testops/__init__.py
testops/listener.py
testops/testops_helper/__init__.py
testops/testops_helper/helper.py
testops_robot-1.0.0.dist-info/METADATA
testops_robot-1.0.0.dist-info/WHEEL
testops_robot-1.0.0.dist-info/top_level.txt
testops_robot-1.0.0.dist-info/RECORD
