Metadata-Version: 2.1
Name: testops-robot
Version: 1.0.0
Summary: Katalon TestOps Robot Plugin
Home-page: https://github.com/katalon-studio/testops-robot
Author: Katalon, LLC. (https://www.katalon.io)
Author-email: info@katalon.io
License: UNKNOWN
Keywords: Katalon,TestOps
Platform: UNKNOWN
Classifier: Programming Language :: Python :: 3
Classifier: Operating System :: OS Independent
Requires-Python: >=3.6
Requires-Dist: testops-commons (>=1.0.6)
